gauss_and_bino_distributions/Binomialdistribution.py
gauss_and_bino_distributions/Gaussiandistribution.py
gauss_and_bino_distributions/Generaldistribution.py
gauss_and_bino_distributions/__init__.py
gauss_and_bino_distributions-0.5.dist-info/METADATA
gauss_and_bino_distributions-0.5.dist-info/WHEEL
gauss_and_bino_distributions-0.5.dist-info/top_level.txt
gauss_and_bino_distributions-0.5.dist-info/RECORD
