Metadata-Version: 2.1
Name: gauss-and-bino-distributions
Version: 0.5
Summary: Gaussian and binomial distributions
Home-page: UNKNOWN
Author: Yip Tuck Wai
Author-email: yiptuckwai@yahoo.com
License: UNKNOWN
Platform: UNKNOWN
